opinionated_ci_pipeline/__init__.py
opinionated_ci_pipeline/py.typed
opinionated_ci_pipeline/_jsii/__init__.py
opinionated_ci_pipeline/_jsii/opinionated-ci-pipeline@4.3.0.jsii.tgz
opinionated_ci_pipeline-4.3.0.dist-info/LICENSE
opinionated_ci_pipeline-4.3.0.dist-info/METADATA
opinionated_ci_pipeline-4.3.0.dist-info/WHEEL
opinionated_ci_pipeline-4.3.0.dist-info/top_level.txt
opinionated_ci_pipeline-4.3.0.dist-info/RECORD
