Metadata-Version: 2.1
Name: opinionated-ci-pipeline
Version: 4.3.0
Summary: CI/CD on AWS with feature-branch builds, developer-environment deployments, and build status notifications.
Home-page: https://github.com/merapar/opinionated-ci-pipeline.git
Author: Maciej Radzikowski<maciej.radzikowski@merapar.com>
License: MIT
Project-URL: Source, https://github.com/merapar/opinionated-ci-pipeline.git
Classifier: Intended Audience :: Developers
Classifier: Operating System :: OS Independent
Classifier: Programming Language :: JavaScript
Classifier: Programming Language :: Python :: 3 :: Only
Classifier: Programming Language :: Python :: 3.9
Classifier: Programming Language :: Python :: 3.10
Classifier: Programming Language :: Python :: 3.11
Classifier: Typing :: Typed
Classifier: Development Status :: 5 - Production/Stable
Classifier: License :: OSI Approved
Requires-Python: ~=3.9
License-File: LICENSE
Requires-Dist: aws-cdk-lib<3.0.0,>=2.151.0
Requires-Dist: constructs<11.0.0,>=10.0.0
Requires-Dist: jsii<2.0.0,>=1.112.0
Requires-Dist: publication>=0.0.3
Requires-Dist: typeguard<4.3.0,>=2.13.3
